freedyn/__init__.py
freedyn/_core.py
freedyn/_ctypes_utils.py
freedyn/_version.py
freedyn/analysis.py
freedyn/cli.py
freedyn/exceptions.py
freedyn/models.py
freedyn/bin/DAT_Dll.dll
freedyn/bin/MBS_Dll.dll
freedyn/bin/PCM_Dll.dll
freedyn/bin/SIM_Dll.dll
freedyn/bin/SOL_Dll.dll
freedyn/bin/TIR_Dll.dll
freedyn/bin/__init__.py
freedyn/bin/exprTk_Dll.dll
freedyn/bin/freedyn.dll
freedyn/bin/libiomp5md.dll
freedyn/bin/tbb12.dll
freedyn-1.0.0.dist-info/licenses/LICENSE
freedyn-1.0.0.dist-info/METADATA
freedyn-1.0.0.dist-info/WHEEL
freedyn-1.0.0.dist-info/entry_points.txt
freedyn-1.0.0.dist-info/top_level.txt
freedyn-1.0.0.dist-info/RECORD
